<annotation>
	<folder>11</folder>
	<filename>07471.jpg</filename>
	<path>F:\比赛\计算机设计大赛——物联网赛道“识虫”\二八分\train\11\07471.jpg</path>
	<source>
		<database>Unknown</database>
	</source>
	<size>
		<width>239</width>
		<height>322</height>
		<depth>3</depth>
	</size>
	<segmented>0</segmented>
	<object>
		<name>rice leafhopper 	</name>
		<pose>Unspecified</pose>
		<truncated>0</truncated>
		<difficult>0</difficult>
		<bndbox>
			<xmin>115</xmin>
			<ymin>39</ymin>
			<xmax>170</xmax>
			<ymax>126</ymax>
		</bndbox>
	</object>
	<object>
		<name>rice leafhopper 	</name>
		<pose>Unspecified</pose>
		<truncated>0</truncated>
		<difficult>0</difficult>
		<bndbox>
			<xmin>20</xmin>
			<ymin>219</ymin>
			<xmax>88</xmax>
			<ymax>313</ymax>
		</bndbox>
	</object>
</annotation>
