<annotation>
	<folder>29</folder>
	<filename>23494.jpg</filename>
	<path>F:\比赛\计算机设计大赛——物联网赛道“识虫”\二八分\train\29\23494.jpg</path>
	<source>
		<database>Unknown</database>
	</source>
	<size>
		<width>473</width>
		<height>321</height>
		<depth>3</depth>
	</size>
	<segmented>0</segmented>
	<object>
		<name>bird cherry-oataphid</name>
		<pose>Unspecified</pose>
		<truncated>0</truncated>
		<difficult>0</difficult>
		<bndbox>
			<xmin>146</xmin>
			<ymin>56</ymin>
			<xmax>227</xmax>
			<ymax>117</ymax>
		</bndbox>
	</object>
	<object>
		<name>bird cherry-oataphid</name>
		<pose>Unspecified</pose>
		<truncated>0</truncated>
		<difficult>0</difficult>
		<bndbox>
			<xmin>212</xmin>
			<ymin>156</ymin>
			<xmax>321</xmax>
			<ymax>239</ymax>
		</bndbox>
	</object>
</annotation>
