<annotation>
	<folder>52</folder>
	<filename>38931.jpg</filename>
	<path>C:\Users\Krooskim\Desktop\dataset\JPEGImages\52\38931.jpg</path>
	<source>
		<database>Unknown</database>
	</source>
	<size>
		<width>800</width>
		<height>600</height>
		<depth>3</depth>
	</size>
	<segmented>0</segmented>
	<object>
		<name>therioaphis maculata Buckton</name>
		<pose>Unspecified</pose>
		<truncated>0</truncated>
		<difficult>0</difficult>
		<bndbox>
			<xmin>12</xmin>
			<ymin>374</ymin>
			<xmax>188</xmax>
			<ymax>538</ymax>
		</bndbox>
	</object>
	<object>
		<name>therioaphis maculata Buckton</name>
		<pose>Unspecified</pose>
		<truncated>0</truncated>
		<difficult>0</difficult>
		<bndbox>
			<xmin>169</xmin>
			<ymin>338</ymin>
			<xmax>357</xmax>
			<ymax>536</ymax>
		</bndbox>
	</object>
	<object>
		<name>therioaphis maculata Buckton</name>
		<pose>Unspecified</pose>
		<truncated>1</truncated>
		<difficult>0</difficult>
		<bndbox>
			<xmin>420</xmin>
			<ymin>1</ymin>
			<xmax>771</xmax>
			<ymax>292</ymax>
		</bndbox>
	</object>
	<object>
		<name>therioaphis maculata Buckton</name>
		<pose>Unspecified</pose>
		<truncated>0</truncated>
		<difficult>0</difficult>
		<bndbox>
			<xmin>399</xmin>
			<ymin>454</ymin>
			<xmax>463</xmax>
			<ymax>572</ymax>
		</bndbox>
	</object>
	<object>
		<name>therioaphis maculata Buckton</name>
		<pose>Unspecified</pose>
		<truncated>0</truncated>
		<difficult>0</difficult>
		<bndbox>
			<xmin>485</xmin>
			<ymin>400</ymin>
			<xmax>544</xmax>
			<ymax>443</ymax>
		</bndbox>
	</object>
</annotation>
