<annotation>
	<folder>55</folder>
	<filename>40102.jpg</filename>
	<path>C:\Users\Krooskim\Desktop\dataset\JPEGImages\55\40102.jpg</path>
	<source>
		<database>Unknown</database>
	</source>
	<size>
		<width>836</width>
		<height>511</height>
		<depth>3</depth>
	</size>
	<segmented>0</segmented>
	<object>
		<name>alfalfa seed chalcid</name>
		<pose>Unspecified</pose>
		<truncated>0</truncated>
		<difficult>0</difficult>
		<bndbox>
			<xmin>32</xmin>
			<ymin>36</ymin>
			<xmax>821</xmax>
			<ymax>494</ymax>
		</bndbox>
	</object>
</annotation>
