<annotation>
	<folder>57</folder>
	<filename>40793.jpg</filename>
	<path>C:\Users\Krooskim\Desktop\dataset\JPEGImages\57\40793.jpg</path>
	<source>
		<database>Unknown</database>
	</source>
	<size>
		<width>900</width>
		<height>600</height>
		<depth>3</depth>
	</size>
	<segmented>0</segmented>
	<object>
		<name>Apolygus lucorum</name>
		<pose>Unspecified</pose>
		<truncated>0</truncated>
		<difficult>0</difficult>
		<bndbox>
			<xmin>140</xmin>
			<ymin>251</ymin>
			<xmax>422</xmax>
			<ymax>479</ymax>
		</bndbox>
	</object>
</annotation>
