<annotation>
	<folder>68</folder>
	<filename>49979.jpg</filename>
	<path>C:\Users\Krooskim\Desktop\dataset\JPEGImages\68\49979.jpg</path>
	<source>
		<database>Unknown</database>
	</source>
	<size>
		<width>800</width>
		<height>533</height>
		<depth>3</depth>
	</size>
	<segmented>0</segmented>
	<object>
		<name>Xylotrechus</name>
		<pose>Unspecified</pose>
		<truncated>0</truncated>
		<difficult>0</difficult>
		<bndbox>
			<xmin>340</xmin>
			<ymin>180</ymin>
			<xmax>663</xmax>
			<ymax>380</ymax>
		</bndbox>
	</object>
</annotation>
