<annotation>
	<folder>73</folder>
	<filename>58213.jpg</filename>
	<path>E:\datapro\dataset\JPEGImages\73\58213.jpg</path>
	<source>
		<database>Unknown</database>
	</source>
	<size>
		<width>200</width>
		<height>300</height>
		<depth>3</depth>
	</size>
	<segmented>0</segmented>
	<object>
		<name>Papilio xuthus</name>
		<pose>Unspecified</pose>
		<truncated>0</truncated>
		<difficult>0</difficult>
		<bndbox>
			<xmin>28</xmin>
			<ymin>29</ymin>
			<xmax>178</xmax>
			<ymax>220</ymax>
		</bndbox>
	</object>
</annotation>
